Metadata-Version: 2.1
Name: destripegui-beta
Version: 1.8.1
Summary: A GUI for automatic pystripe destriping
Home-page: https://github.com/lifecanvastechnologies
Author: LifeCanvas Technologies
License: MIT
Classifier: Development Status :: 4 - Beta
Classifier: Programming Language :: Python :: 3.7
License-File: LICENSE.txt
